Dgame/Dgame.py
Dgame/__init__.py
Dgame-2.2.dist-info/METADATA
Dgame-2.2.dist-info/WHEEL
Dgame-2.2.dist-info/top_level.txt
Dgame-2.2.dist-info/RECORD
