Metadata-Version: 2.1
Name: Dgame
Version: 2.2
Summary: discord game To make changes easily
Home-page: https://github.com/0xfmc/dgame
Author: admin_01S
Author-email: discord-api@naver.com
License: MIT
Platform: UNKNOWN
Classifier: Programming Language :: Python :: 3.6
Classifier: Programming Language :: Python :: 3.7
Classifier: Programming Language :: Python :: 3.8
Requires-Python: >=3.6
